{
    "id": "set_awaymode",
    "title": {
        "en": "Set lock mode (home/away)",
        "sv": "Ställ in borta/hemma",
        "no": "Still inn hjemme-/bortemodus"
    },
    "titleFormatted": {
        "en": "Set lock mode [[mode]]",
        "no": "Sett hjemme-/bortemodus til [[mode]]"
    },
    "args": [
        {
            "name": "device",
            "type": "device",
            "filter": "driver_id=IDlock150"
        },
        {
            "name": "mode",
            "type": "dropdown",
            "values": [
                {
                    "id": "0",
                    "label": {
                        "en": "Disabled Away mode and Manual locking mode",
                        "sv": "Inaktivera Bortaläge, Manuell låsning",
                        "no": "Deaktivert Bortemodus og Manuell låsing"
                    }
                },
                {
                    "id": "1",
                    "label": {
                        "en": "Disabled Away mode and Automatic locking mode",
                        "sv": "Inaktivera Bortaläge, Automatisk låsning (Standard)",
                        "no": "Deaktivert Bortemodus og Automatisk låsing (standard)"
                    }
                },
                {
                    "id": "3",
                    "label": {
                        "en": "Away mode and Automatic locking mode",
                        "sv": "Aktiverat Bortaläge, Automatisk låsning",
                        "no": "Aktivert Bortemodus og Automatisk låsing"
                    }
                },
                {
                    "id": "2",
                    "label": {
                        "en": "Away mode and Manual locking mode",
                        "sv": "Aktiverat Bortaläge, Manuell låsning",
                        "no": "Aktivert Bortemodus og Manuell låsing"
                    }
                }
            ]
        }
    ]
}
